<?xml version="1.0" encoding="utf-8" ?>
<dwsync>
<file name="page.php" server="34.219.18.77//opt/bitnami/apps/wordpress/htdocs/" local="132179933070000000" remote="132179933070000000" Dst="1" />
<file name="header.php" server="34.219.18.77//opt/bitnami/apps/wordpress/htdocs/" local="132179933070000000" remote="132179933070000000" Dst="1" />
<file name="comments.php" server="34.219.18.77//opt/bitnami/apps/wordpress/htdocs/" local="132179933070000000" remote="132179933070000000" Dst="1" />
<file name="license.txt" server="34.219.18.77//opt/bitnami/apps/wordpress/htdocs/" local="132179933070000000" remote="132179933070000000" Dst="1" />
<file name="front-page.php" server="34.219.18.77//opt/bitnami/apps/wordpress/htdocs/" local="132179933070000000" remote="132179933070000000" Dst="1" />
<file name="footer.php" server="34.219.18.77//opt/bitnami/apps/wordpress/htdocs/" local="132179933070000000" remote="132179933070000000" Dst="1" />
<file name="screenshot.png" server="34.219.18.77//opt/bitnami/apps/wordpress/htdocs/" local="132179933070000000" remote="132179933070000000" Dst="1" />
<file name="sidebar.php" server="34.219.18.77//opt/bitnami/apps/wordpress/htdocs/" local="132179933070000000" remote="132179933070000000" Dst="1" />
<file name="front-page-content.php" server="34.219.18.77//opt/bitnami/apps/wordpress/htdocs/" local="132179933070000000" remote="132179933070000000" Dst="1" />
<file name="searchform.php" server="34.219.18.77//opt/bitnami/apps/wordpress/htdocs/" local="132179933070000000" remote="132179933070000000" Dst="1" />
<file name="sidebar-footer.php" server="34.219.18.77//opt/bitnami/apps/wordpress/htdocs/" local="132179933070000000" remote="132179933070000000" Dst="1" />
<file name="readme.txt" server="34.219.18.77//opt/bitnami/apps/wordpress/htdocs/" local="132179933070000000" remote="132179933070000000" Dst="1" />
<file name="archive.php" server="34.219.18.77//opt/bitnami/apps/wordpress/htdocs/" local="132179933070000000" remote="132179933070000000" Dst="1" />
<file name="search.php" server="34.219.18.77//opt/bitnami/apps/wordpress/htdocs/" local="132179933070000000" remote="132179933070000000" Dst="1" />
<file name="featured-box.php" server="34.219.18.77//opt/bitnami/apps/wordpress/htdocs/" local="132179933070000000" remote="132179933070000000" Dst="1" />
<file name="index.php" server="34.219.18.77//opt/bitnami/apps/wordpress/htdocs/" local="132179933070000000" remote="132179933070000000" Dst="1" />
<file name="single.php" server="34.219.18.77//opt/bitnami/apps/wordpress/htdocs/" local="132179933070000000" remote="132179933070000000" Dst="1" />
<file name="style.css" server="34.219.18.77//opt/bitnami/apps/wordpress/htdocs/" local="132179933070000000" remote="132179933070000000" Dst="1" />
<file name="style-responsive.css" server="34.219.18.77//opt/bitnami/apps/wordpress/htdocs/" local="132179933070000000" remote="132179933070000000" Dst="1" />
<file name="404.php" server="34.219.18.77//opt/bitnami/apps/wordpress/htdocs/" local="132179933070000000" remote="132179933070000000" Dst="1" />
<file name="functions.php" server="34.219.18.77//opt/bitnami/apps/wordpress/htdocs/" local="132179933070000000" remote="132179933070000000" Dst="1" />
<file name="blog.php" server="34.219.18.77//opt/bitnami/apps/wordpress/htdocs/" local="132179933070000000" remote="132179933070000000" Dst="1" />
<file name="fullwidth.php" server="34.219.18.77//opt/bitnami/apps/wordpress/htdocs/" local="132179933070000000" remote="132179933070000000" Dst="1" />
</dwsync>